{
  "formatVersion": 1,
  "database": {
    "version": 2,
    "identityHash": "091da13a2c86e7ef70c010dde2279a5b",
    "entities": [
      {
        "tableName": "profiles",
        "createSql": "CREATE TABLE IF NOT EXISTS `${TABLE_NAME}` (`id` INTEGER PRIMARY KEY AUTOINCREMENT NOT NULL, `profile_id` INTEGER NOT NULL, `email` TEXT NOT NULL, `phone_number` TEXT, `gender` INTEGER, `culture` INTEGER, `birthday` TEXT, `first_name` TEXT NOT NULL, `last_name` TEXT NOT NULL, `username` TEXT NOT NULL, `password` TEXT NOT NULL, `avatar_path` TEXT, `cover_path` TEXT, `request_token` TEXT NOT NULL, `session_id` TEXT NOT NULL)",
        "fields": [
          {
            "fieldPath": "id",
            "columnName": "id",
            "affinity": "INTEGER",
            "notNull": true
          },
          {
            "fieldPath": "profileId",
            "columnName": "profile_id",
            "affinity": "INTEGER",
            "notNull": true
          },
          {
            "fieldPath": "email",
            "columnName": "email",
            "affinity": "TEXT",
            "notNull": true
          },
          {
            "fieldPath": "phoneNumber",
            "columnName": "phone_number",
            "affinity": "TEXT",
            "notNull": false
          },
          {
            "fieldPath": "gender",
            "columnName": "gender",
            "affinity": "INTEGER",
            "notNull": false
          },
          {
            "fieldPath": "culture",
            "columnName": "culture",
            "affinity": "INTEGER",
            "notNull": false
          },
          {
            "fieldPath": "birthday",
            "columnName": "birthday",
            "affinity": "TEXT",
            "notNull": false
          },
          {
            "fieldPath": "firstName",
            "columnName": "first_name",
            "affinity": "TEXT",
            "notNull": true
          },
          {
            "fieldPath": "lastName",
            "columnName": "last_name",
            "affinity": "TEXT",
            "notNull": true
          },
          {
            "fieldPath": "userName",
            "columnName": "username",
            "affinity": "TEXT",
            "notNull": true
          },
          {
            "fieldPath": "password",
            "columnName": "password",
            "affinity": "TEXT",
            "notNull": true
          },
          {
            "fieldPath": "avatarPath",
            "columnName": "avatar_path",
            "affinity": "TEXT",
            "notNull": false
          },
          {
            "fieldPath": "coverPath",
            "columnName": "cover_path",
            "affinity": "TEXT",
            "notNull": false
          },
          {
            "fieldPath": "requestToken",
            "columnName": "request_token",
            "affinity": "TEXT",
            "notNull": true
          },
          {
            "fieldPath": "sessionId",
            "columnName": "session_id",
            "affinity": "TEXT",
            "notNull": true
          }
        ],
        "primaryKey": {
          "autoGenerate": true,
          "columnNames": [
            "id"
          ]
        },
        "indices": [],
        "foreignKeys": []
      },
      {
        "tableName": "profile_avatars",
        "createSql": "CREATE TABLE IF NOT EXISTS `${TABLE_NAME}` (`picture_id` INTEGER NOT NULL, `profile_id` INTEGER NOT NULL, `picture` TEXT, PRIMARY KEY(`picture_id`), FOREIGN KEY(`profile_id`) REFERENCES `profiles`(`id`) ON UPDATE CASCADE ON DELETE CASCADE )",
        "fields": [
          {
            "fieldPath": "pictureId",
            "columnName": "picture_id",
            "affinity": "INTEGER",
            "notNull": true
          },
          {
            "fieldPath": "profileId",
            "columnName": "profile_id",
            "affinity": "INTEGER",
            "notNull": true
          },
          {
            "fieldPath": "picture",
            "columnName": "picture",
            "affinity": "TEXT",
            "notNull": false
          }
        ],
        "primaryKey": {
          "autoGenerate": false,
          "columnNames": [
            "picture_id"
          ]
        },
        "indices": [
          {
            "name": "index_profile_avatars_profile_id",
            "unique": false,
            "columnNames": [
              "profile_id"
            ],
            "orders": [],
            "createSql": "CREATE INDEX IF NOT EXISTS `index_profile_avatars_profile_id` ON `${TABLE_NAME}` (`profile_id`)"
          }
        ],
        "foreignKeys": [
          {
            "table": "profiles",
            "onDelete": "CASCADE",
            "onUpdate": "CASCADE",
            "columns": [
              "profile_id"
            ],
            "referencedColumns": [
              "id"
            ]
          }
        ]
      },
      {
        "tableName": "conversation_users",
        "createSql": "CREATE TABLE IF NOT EXISTS `${TABLE_NAME}` (`id` TEXT NOT NULL, `userId` TEXT NOT NULL, `profileId` TEXT NOT NULL, `avatarUrl` TEXT, `firstName` TEXT NOT NULL, `lastName` TEXT NOT NULL, `isUnread` INTEGER NOT NULL, `isMainUser` INTEGER NOT NULL, `conversation_id` TEXT, PRIMARY KEY(`id`))",
        "fields": [
          {
            "fieldPath": "id",
            "columnName": "id",
            "affinity": "TEXT",
            "notNull": true
          },
          {
            "fieldPath": "userId",
            "columnName": "userId",
            "affinity": "TEXT",
            "notNull": true
          },
          {
            "fieldPath": "profileId",
            "columnName": "profileId",
            "affinity": "TEXT",
            "notNull": true
          },
          {
            "fieldPath": "avatarUrl",
            "columnName": "avatarUrl",
            "affinity": "TEXT",
            "notNull": false
          },
          {
            "fieldPath": "firstName",
            "columnName": "firstName",
            "affinity": "TEXT",
            "notNull": true
          },
          {
            "fieldPath": "lastName",
            "columnName": "lastName",
            "affinity": "TEXT",
            "notNull": true
          },
          {
            "fieldPath": "isUnread",
            "columnName": "isUnread",
            "affinity": "INTEGER",
            "notNull": true
          },
          {
            "fieldPath": "isMainUser",
            "columnName": "isMainUser",
            "affinity": "INTEGER",
            "notNull": true
          },
          {
            "fieldPath": "conversationId",
            "columnName": "conversation_id",
            "affinity": "TEXT",
            "notNull": false
          }
        ],
        "primaryKey": {
          "autoGenerate": false,
          "columnNames": [
            "id"
          ]
        },
        "indices": [
          {
            "name": "index_conversation_users_conversation_id",
            "unique": false,
            "columnNames": [
              "conversation_id"
            ],
            "orders": [],
            "createSql": "CREATE INDEX IF NOT EXISTS `index_conversation_users_conversation_id` ON `${TABLE_NAME}` (`conversation_id`)"
          }
        ],
        "foreignKeys": []
      },
      {
        "tableName": "message_attachments",
        "createSql": "CREATE TABLE IF NOT EXISTS `${TABLE_NAME}` (`id` TEXT NOT NULL, `message_id` TEXT NOT NULL, `fileId` TEXT, `mimeType` TEXT, `name` TEXT, `path` TEXT, `previewPath` TEXT, `titleAttribute` TEXT, PRIMARY KEY(`id`))",
        "fields": [
          {
            "fieldPath": "id",
            "columnName": "id",
            "affinity": "TEXT",
            "notNull": true
          },
          {
            "fieldPath": "messageId",
            "columnName": "message_id",
            "affinity": "TEXT",
            "notNull": true
          },
          {
            "fieldPath": "file.fileId",
            "columnName": "fileId",
            "affinity": "TEXT",
            "notNull": false
          },
          {
            "fieldPath": "file.mimeType",
            "columnName": "mimeType",
            "affinity": "TEXT",
            "notNull": false
          },
          {
            "fieldPath": "file.name",
            "columnName": "name",
            "affinity": "TEXT",
            "notNull": false
          },
          {
            "fieldPath": "file.path",
            "columnName": "path",
            "affinity": "TEXT",
            "notNull": false
          },
          {
            "fieldPath": "file.previewPath",
            "columnName": "previewPath",
            "affinity": "TEXT",
            "notNull": false
          },
          {
            "fieldPath": "file.titleAttribute",
            "columnName": "titleAttribute",
            "affinity": "TEXT",
            "notNull": false
          }
        ],
        "primaryKey": {
          "autoGenerate": false,
          "columnNames": [
            "id"
          ]
        },
        "indices": [
          {
            "name": "index_message_attachments_message_id",
            "unique": false,
            "columnNames": [
              "message_id"
            ],
            "orders": [],
            "createSql": "CREATE INDEX IF NOT EXISTS `index_message_attachments_message_id` ON `${TABLE_NAME}` (`message_id`)"
          }
        ],
        "foreignKeys": []
      },
      {
        "tableName": "movies",
        "createSql": "CREATE TABLE IF NOT EXISTS `${TABLE_NAME}` (`id` INTEGER NOT NULL, `adult` INTEGER NOT NULL, `backdropPath` TEXT, `originalLanguage` TEXT NOT NULL, `originalTitle` TEXT NOT NULL, `overview` TEXT NOT NULL, `popularity` REAL NOT NULL, `posterPath` TEXT, `releaseDate` TEXT NOT NULL, `title` TEXT NOT NULL, `video` INTEGER NOT NULL, `voteAverage` REAL NOT NULL, `voteCount` INTEGER NOT NULL, `genreIds` TEXT NOT NULL, PRIMARY KEY(`id`))",
        "fields": [
          {
            "fieldPath": "id",
            "columnName": "id",
            "affinity": "INTEGER",
            "notNull": true
          },
          {
            "fieldPath": "adult",
            "columnName": "adult",
            "affinity": "INTEGER",
            "notNull": true
          },
          {
            "fieldPath": "backdropPath",
            "columnName": "backdropPath",
            "affinity": "TEXT",
            "notNull": false
          },
          {
            "fieldPath": "originalLanguage",
            "columnName": "originalLanguage",
            "affinity": "TEXT",
            "notNull": true
          },
          {
            "fieldPath": "originalTitle",
            "columnName": "originalTitle",
            "affinity": "TEXT",
            "notNull": true
          },
          {
            "fieldPath": "overview",
            "columnName": "overview",
            "affinity": "TEXT",
            "notNull": true
          },
          {
            "fieldPath": "popularity",
            "columnName": "popularity",
            "affinity": "REAL",
            "notNull": true
          },
          {
            "fieldPath": "posterPath",
            "columnName": "posterPath",
            "affinity": "TEXT",
            "notNull": false
          },
          {
            "fieldPath": "releaseDate",
            "columnName": "releaseDate",
            "affinity": "TEXT",
            "notNull": true
          },
          {
            "fieldPath": "title",
            "columnName": "title",
            "affinity": "TEXT",
            "notNull": true
          },
          {
            "fieldPath": "video",
            "columnName": "video",
            "affinity": "INTEGER",
            "notNull": true
          },
          {
            "fieldPath": "voteAverage",
            "columnName": "voteAverage",
            "affinity": "REAL",
            "notNull": true
          },
          {
            "fieldPath": "voteCount",
            "columnName": "voteCount",
            "affinity": "INTEGER",
            "notNull": true
          },
          {
            "fieldPath": "genreIds",
            "columnName": "genreIds",
            "affinity": "TEXT",
            "notNull": true
          }
        ],
        "primaryKey": {
          "autoGenerate": false,
          "columnNames": [
            "id"
          ]
        },
        "indices": [],
        "foreignKeys": []
      }
    ],
    "views": [],
    "setupQueries": [
      "CREATE TABLE IF NOT EXISTS room_master_table (id INTEGER PRIMARY KEY,identity_hash TEXT)",
      "INSERT OR REPLACE INTO room_master_table (id,identity_hash) VALUES(42, '091da13a2c86e7ef70c010dde2279a5b')"
    ]
  }
}